tiktokimage/__init__.py
tiktokimage/convert.py
tiktokimage-0.2.dist-info/METADATA
tiktokimage-0.2.dist-info/WHEEL
tiktokimage-0.2.dist-info/entry_points.txt
tiktokimage-0.2.dist-info/top_level.txt
tiktokimage-0.2.dist-info/RECORD
